path_tree_generator/__init__.py
path_tree_generator/models/__init__.py
path_tree_generator/models/list_entries.py
path_tree_generator/path_tree.py
path_tree_generator-0.3.1.dist-info/LICENSE
path_tree_generator-0.3.1.dist-info/WHEEL
path_tree_generator-0.3.1.dist-info/METADATA
path_tree_generator-0.3.1.dist-info/RECORD
