Metadata-Version: 2.1
Name: path-tree-generator
Version: 0.3.1
Summary: Generate tree-like directory listings for humans and output them as str, list[str], dict or json.
Home-page: https://github.com/dl6nm/path-tree-generator
License: MIT
Keywords: path,tree,generator,json,converter,directory,dir,human-readable,tree-like,linux
Author: DL6NM
Author-email: mail@dl6nm.de
Requires-Python: >=3.10,<4.0
Classifier: Development Status :: 4 - Beta
Classifier: Intended Audience :: Developers
Classifier: Intended Audience :: Information Technology
Classifier: Intended Audience :: Other Audience
Classifier: Intended Audience :: System Administrators
Classifier: License :: OSI Approved :: MIT License
Classifier: Operating System :: MacOS
Classifier: Operating System :: Microsoft
Classifier: Operating System :: Microsoft :: Windows
Classifier: Operating System :: POSIX
Classifier: Operating System :: POSIX :: Linux
Classifier: Programming Language :: Python :: 3
Classifier: Programming Language :: Python :: 3.10
Classifier: Topic :: Software Development
Classifier: Topic :: System :: Filesystems
Classifier: Topic :: Utilities
Classifier: Typing :: Typed
Requires-Dist: pydantic (>=1.9.1,<2.0.0)
Project-URL: Repository, https://github.com/dl6nm/path-tree-generator
